ida_lib/__init__.py
ida_lib/global_parameters.py
ida_lib/visualization.py
ida_lib/core/__init__.py
ida_lib/core/pipeline.py
ida_lib/core/pipeline_functional.py
ida_lib/core/pipeline_geometric_ops.py
ida_lib/core/pipeline_local_ops.py
ida_lib/core/pipeline_operations.py
ida_lib/core/pipeline_pixel_ops.py
ida_lib/image_augmentation/__init__.py
ida_lib/image_augmentation/augment_to_disk.py
ida_lib/image_augmentation/data_loader.py
ida_lib/operations/__init__.py
ida_lib/operations/geometry_ops_functional.py
ida_lib/operations/pixel_ops_functional.py
ida_lib/operations/transforms.py
ida_lib/operations/utils.py
ida_lib-0.1.dist-info/LICENCE
ida_lib-0.1.dist-info/METADATA
ida_lib-0.1.dist-info/WHEEL
ida_lib-0.1.dist-info/top_level.txt
ida_lib-0.1.dist-info/RECORD
